[{"pk": 1, "model": "Blog.myblog", "fields": {"content": "gb", "version": 2, "pub_date": "2014-10-04T14:16:32.190Z", "title": "1st"}}, {"pk": 2, "model": "Blog.myblog", "fields": {"content": "djldld,\r\nedited oncefff", "version": 3, "pub_date": "2014-10-04T14:16:47.766Z", "title": "second"}}, {"pk": 3, "model": "Blog.myblog", "fields": {"content": "vlmlmlmlm", "version": 1, "pub_date": "2014-10-04T14:19:43.599Z", "title": "third"}}, {"pk": 4, "model": "Blog.myblog", "fields": {"content": "YO!", "version": 0, "pub_date": "2014-10-04T14:19:43.599Z", "title": "fourth"}}]